{
  "transactions": [
    {
      "contractId": "ct_zq9PGMYXx9TdbxFMjc6U5FcPzVBYeZqDjdZbJUxt1WTamNhYt",
      "recipientAddress": null,
      "proposedAmount": null,
      "id": 25
    },
    {
      "contractId": "ct_6Ftdx33P64Hs4D8DfBwm1AM8iQPwnUo3LCybuBHC8CUWkFZ2K",
      "recipientAddress": null,
      "proposedAmount": null,
      "id": 26
    },
    {
      "contractId": "ct_q4SxCJLTro8qrxnMWAM9YzU5B1KhWunnQwfBjpwMzbbiTp4TR",
      "recipientAddress": null,
      "proposedAmount": null,
      "id": 27
    },
    {
      "contractId": "ct_2X8WxjebmH8XwPGquCaFYuRaRAqdaK3kFuVDJ5jW5aJFsYUr2t",
      "recipientAddress": null,
      "proposedAmount": null,
      "id": 28,
      "revokedBy": null,
      "sentBy": null
    }
  ]
}
